Metadata-Version: 2.1
Name: Astrology-Aries
Version: 0.0.5.dev447
Summary: Python package providing shortcuts to tasks like accessing files on the cloud, running background tasks, configuring logging, etc.
Home-page: https://github.com/qiuosier/Aries
Author: Qiu Qin
Author-email: qiuosier@gmail.com
License: UNKNOWN
Platform: UNKNOWN
Classifier: Programming Language :: Python :: 3
Classifier: License :: OSI Approved :: MIT License
Classifier: Operating System :: OS Independent
Requires-Python: >=3.6
Requires-Dist: openpyxl (==2.4.8)
Requires-Dist: requests (==2.23.0)
Requires-Dist: google-cloud-core (==1.3.0)
Requires-Dist: google-cloud-storage (==1.26.0)
Requires-Dist: boto3 (==1.12.16)
Requires-Dist: lxml (>=4.5.1)
Requires-Dist: plotly (>=4.5.0)
